{
  "setting": {},
  "condition": {
    "plugin": {
      "list": []
    },
    "game": {
      "list": []
    },
    "gamePlugin": {
      "list": []
    },
    "miniprogram": {
      "list": [
        {
          "name": "首页",
          "pathName": "pages/home/index",
          "query": "",
          "scene": null
        },
        {
          "name": "prod2",
          "pathName": "pages/game/index",
          "query": "id=8937eaa961174d4304a1bff3618c98c0",
          "scene": null
        },
        {
          "name": "prod",
          "pathName": "pages/game/index",
          "query": "id=cbddf0af60d3e726122f2eb25b84e349",
          "scene": null
        },
        {
          "name": "ranking",
          "pathName": "pages/ranking/index",
          "query": "",
          "scene": null
        },
        {
          "name": "大厅",
          "pathName": "pages/hall/index",
          "query": "",
          "scene": null
        },
        {
          "name": "历史记录",
          "pathName": "pages/history/index",
          "query": "",
          "scene": null
        },
        {
          "name": "游戏指导",
          "pathName": "pages/guide/index",
          "query": "id=2d44d6c26110f22f040229aa4422ad8b",
          "scene": null
        }
      ]
    }
  }
}